AUTHORS
CHANGELOG
COPYING
Editra.pyw
FAQ
INSTALL
MANIFEST.in
Makefile
NEWS
README
THANKS
TODO
__init__.py
editra
editra-installer.nsi
editra_pylintrc
launcher.py
setup.cfg
setup.py
./__init__.py
./launcher.py
Editra.egg-info/PKG-INFO
Editra.egg-info/SOURCES.txt
Editra.egg-info/dependency_links.txt
Editra.egg-info/requires.txt
Editra.egg-info/top_level.txt
docs/CHANGELOG_1
docs/CHANGELOG_2
docs/CHANGELOG_3
docs/CHANGELOG_4
docs/CHANGELOG_5
docs/CHANGELOG_6
docs/CHANGELOG_7
docs/editra_style_sheets.txt
docs/launch.xml
docs/syntax.xml
docs/doc_inputs/mainpage.dox
docs/doc_inputs/interface_docs/editorctxmenu.dox
docs/doc_inputs/interface_docs/hovertips.dox
docs/doc_inputs/notify_docs/themenotify.dox
ekeys/VisualStudio.ekeys
include/python2.5/darwin/pyconfig.h
include/windows/gdiplus.dll
include/windows/mfc90.dll
include/windows/mfc90u.dll
include/windows/msvcr90.dll
locale/be_BY/LC_MESSAGES/Editra.mo
locale/bg_BG/LC_MESSAGES/Editra.mo
locale/ca_ES/LC_MESSAGES/Editra.mo
locale/ca_ES@valencia/LC_MESSAGES/Editra.mo
locale/cs_CZ/LC_MESSAGES/Editra.mo
locale/da_DK/LC_MESSAGES/Editra.mo
locale/de_DE/LC_MESSAGES/Editra.mo
locale/el_GR/LC_MESSAGES/Editra.mo
locale/en_GB/LC_MESSAGES/Editra.mo
locale/en_US/LC_MESSAGES/Editra.mo
locale/eo/LC_MESSAGES/Editra.mo
locale/es_ES/LC_MESSAGES/Editra.mo
locale/et_EE/LC_MESSAGES/Editra.mo
locale/eu_ES/LC_MESSAGES/Editra.mo
locale/fa_IR/LC_MESSAGES/Editra.mo
locale/fi_FI/LC_MESSAGES/Editra.mo
locale/fr_FR/LC_MESSAGES/Editra.mo
locale/gl_ES/LC_MESSAGES/Editra.mo
locale/he_IL/LC_MESSAGES/Editra.mo
locale/hr_HR/LC_MESSAGES/Editra.mo
locale/hu_HU/LC_MESSAGES/Editra.mo
locale/id_ID/LC_MESSAGES/Editra.mo
locale/it_IT/LC_MESSAGES/Editra.mo
locale/ja_JP/LC_MESSAGES/Editra.mo
locale/ka_GE/LC_MESSAGES/Editra.mo
locale/ko_KR/LC_MESSAGES/Editra.mo
locale/lt_LT/LC_MESSAGES/Editra.mo
locale/lv_LV/LC_MESSAGES/Editra.mo
locale/ms_MY/LC_MESSAGES/Editra.mo
locale/nb_NO/LC_MESSAGES/Editra.mo
locale/nl_NL/LC_MESSAGES/Editra.mo
locale/nn_NO/LC_MESSAGES/Editra.mo
locale/oc/LC_MESSAGES/Editra.mo
locale/pl_PL/LC_MESSAGES/Editra.mo
locale/pt_BR/LC_MESSAGES/Editra.mo
locale/pt_PT/LC_MESSAGES/Editra.mo
